rettij/__init__.py
rettij/__main__.py
rettij/abstract_scheduled_sequence.py
rettij/abstract_script_sequence.py
rettij/network_manager.py
rettij/rettij.py
rettij/simulation_manager.py
rettij/standalone.py
rettij/step.py
rettij/cli/__init__.py
rettij/cli/_init_interpreter.py
rettij/cli/_interactive_history_console.py
rettij/cli/cli.py
rettij/commands/__init__.py
rettij/commands/async_script_command.py
rettij/commands/command.py
rettij/commands/command_result.py
rettij/commands/download_router_config_file_command.py
rettij/commands/execute_router_config_command.py
rettij/commands/nmap_command.py
rettij/commands/open_shell_command.py
rettij/commands/ping_command.py
rettij/commands/put_file_command.py
rettij/commands/retrieve_file_command.py
rettij/commands/run_command.py
rettij/commands/stop_command.py
rettij/commands/update_router_config_file_command.py
rettij/common/__init__.py
rettij/common/constants.py
rettij/common/data_rate.py
rettij/common/file_permissions.py
rettij/common/is_suited_host_system.py
rettij/common/logging_utilities.py
rettij/common/uid.py
rettij/common/validated_path.py
rettij/common/yaml_loader_with_line_numbers.py
rettij/common/logging/__init__.py
rettij/common/logging/monitoring_logging.py
rettij/components/README.md
rettij/components/host/README.md
rettij/components/hub/hub.yaml
rettij/components/simple-router/README.md
rettij/components/simple-router/simple-router.yaml
rettij/components/simple-router/hooks/post-deploy.py
rettij/components/simple-runner/simple-runner.yaml
rettij/components/simple-switch/simple-switch.yaml
rettij/cosim/__init__.py
rettij/cosim/rettij_mosaik.py
rettij/examples/README.md
rettij/examples/sequences/scheduled_ping_sequence.py
rettij/examples/sequences/script_ping_sequence.py
rettij/examples/sequences/tcp_dump_sequence.py
rettij/examples/topologies/simple-switch_topology.yml
rettij/examples/topologies/simple-switch_topology_with_host.yml
rettij/exceptions/__init__.py
rettij/exceptions/copy_exception.py
rettij-1.8.3.dist-info/LICENSE
rettij-1.8.3.dist-info/METADATA
rettij-1.8.3.dist-info/WHEEL
rettij-1.8.3.dist-info/entry_points.txt
rettij-1.8.3.dist-info/top_level.txt
rettij-1.8.3.dist-info/RECORD
