Metadata-Version: 2.1
Name: rettij
Version: 1.8.3
Summary: rettij is an easy-to-use, scalable and co-simulation-capable ICT network simulator based on Kubernetes. It is designed for use with [Mosaik](https://mosaik.offis.de/) but can also be used standalone as a plain ICT network simulator.
Home-page: https://frihsb.gitlab.io/rettij/
Author: Forschungsgruppe Rechnernetze und Informationssicherheit
Author-email: fri@hs-bremen.de
License: MIT
Project-URL: Source Code, https://gitlab.com/frihsb/rettij
Project-URL: Documentation, https://frihsb.gitlab.io/rettij
Project-URL: Changelog, https://gitlab.com/frihsb/rettij/-/releases
Project-URL: Issue Tracker, https://gitlab.com/frihsb/rettij/-/issues
Classifier: Programming Language :: Python :: 3.8
Classifier: Development Status :: 5 - Production/Stable
Classifier: License :: OSI Approved :: MIT License
Classifier: Operating System :: POSIX :: Linux
Classifier: Operating System :: MacOS :: MacOS X
Classifier: Environment :: Console
Classifier: Intended Audience :: Science/Research
Classifier: Intended Audience :: Information Technology
Classifier: Intended Audience :: Education
Requires-Python: >=3.8
License-File: LICENSE
Requires-Dist: kubernetes ~=17.17.0
Requires-Dist: PyYAML ~=6.0.1
Requires-Dist: requests ~=2.25.1
Requires-Dist: jsonschema ~=3.2.0
Requires-Dist: jsonref ~=0.2
Requires-Dist: urllib3 ~=1.26.1
Requires-Dist: influxdb-client ~=1.27.0
Requires-Dist: mosaik-api ~=3.0.0
